LICENSE
MANIFEST.in
README.rst
setup.py
mezzanine_sirtrevor.egg-info/PKG-INFO
mezzanine_sirtrevor.egg-info/SOURCES.txt
mezzanine_sirtrevor.egg-info/dependency_links.txt
mezzanine_sirtrevor.egg-info/not-zip-safe
mezzanine_sirtrevor.egg-info/requires.txt
mezzanine_sirtrevor.egg-info/top_level.txt
sirtrevor/__init__.py
sirtrevor/admin.py
sirtrevor/blocks.py
sirtrevor/conf.py
sirtrevor/fields.py
sirtrevor/filters.py
sirtrevor/forms.py
sirtrevor/models.py
sirtrevor/tests.py
sirtrevor/urls.py
sirtrevor/utils.py
sirtrevor/views.py
sirtrevor/widgets.py
sirtrevor/static/mezzanine/js/editable.js
sirtrevor/static/sirtrevor/.DS_Store
sirtrevor/static/sirtrevor/init.js
sirtrevor/static/sirtrevor/mezz-sir-trevor.css
sirtrevor/static/sirtrevor/mezz-sir-trevor.js
sirtrevor/static/sirtrevor/components/.DS_Store
sirtrevor/static/sirtrevor/components/Eventable/.bower.json
sirtrevor/static/sirtrevor/components/Eventable/.gitignore
sirtrevor/static/sirtrevor/components/Eventable/README.md
sirtrevor/static/sirtrevor/components/Eventable/bower.json
sirtrevor/static/sirtrevor/components/Eventable/eventable.js
sirtrevor/static/sirtrevor/components/Eventable/package.json
sirtrevor/static/sirtrevor/components/jquery/.bower.json
sirtrevor/static/sirtrevor/components/jquery/.gitignore
sirtrevor/static/sirtrevor/components/jquery/README.md
sirtrevor/static/sirtrevor/components/jquery/component.json
sirtrevor/static/sirtrevor/components/jquery/composer.json
sirtrevor/static/sirtrevor/components/jquery/jquery-migrate.js
sirtrevor/static/sirtrevor/components/jquery/jquery-migrate.min.js
sirtrevor/static/sirtrevor/components/jquery/jquery.js
sirtrevor/static/sirtrevor/components/jquery/jquery.min.js
sirtrevor/static/sirtrevor/components/jquery/jquery.min.map
sirtrevor/static/sirtrevor/components/jquery/package.json
sirtrevor/static/sirtrevor/components/sir-trevor-js/.DS_Store
sirtrevor/static/sirtrevor/components/sir-trevor-js/.bower.json
sirtrevor/static/sirtrevor/components/sir-trevor-js/CHANGELOG.md
sirtrevor/static/sirtrevor/components/sir-trevor-js/Gruntfile.js
sirtrevor/static/sirtrevor/components/sir-trevor-js/MIT-LICENCE
sirtrevor/static/sirtrevor/components/sir-trevor-js/Readme.md
