Metadata-Version: 1.1
Name: mezzanine-sirtrevor
Version: 0.1.0
Summary: Sir Trevor editor for Mezzanine
Home-page: https://github.com/thecodinghouse/mezzanine-sirtrevor
Author: Abhinav Sohani
Author-email: thecodinghouse12@gmail.com
License: MIT License
Download-URL: https://github.com/thecodinghouse/mezzanine-sirtrevor/tarball/v0.1.0
Platform: UNKNOWN
Classifier: Environment :: Web Environment
Classifier: Framework :: Django
Classifier: Intended Audience :: Developers
Classifier: License :: OSI Approved :: MIT License
Classifier: Operating System :: OS Independent
Classifier: Programming Language :: Python
Classifier: Programming Language :: Python :: 2
Classifier: Programming Language :: Python :: 2.6
Classifier: Programming Language :: Python :: 2.7
Classifier: Programming Language :: Python :: 3
Classifier: Programming Language :: Python :: 3.3
Classifier: Topic :: Internet :: WWW/HTTP
Classifier: Topic :: Internet :: WWW/HTTP :: Dynamic Content
